smev_services_dod_certificate/__init__.py
smev_services_dod_certificate/converter.py
smev_services_dod_certificate/service.py
smev_services_dod_certificate/domain/__init__.py
smev_services_dod_certificate/domain/model/__init__.py
smev_services_dod_certificate/domain/model/const.py
smev_services_dod_certificate/domain/model/request.py
smev_services_dod_certificate/domain/model/response.py
smev_services_dod_certificate/schemas/SOMC.xsd
smev_services_dod_certificate-0.2.0.dist-info/METADATA
smev_services_dod_certificate-0.2.0.dist-info/WHEEL
smev_services_dod_certificate-0.2.0.dist-info/top_level.txt
smev_services_dod_certificate-0.2.0.dist-info/RECORD
